{"ls":[{"op":"PANELTITLE.CAPTION","s":"コンテンツライブラリの管理"},{"op":"PANELEXPLANATION.CAPTION","s":"以下のコンテンツを選択して、ライブラリに新しいコンテンツを追加したり、コンテンツを編集したりできます"},{"op":"SEARCH.PLACEHOLDER","s":"名前、説明、ファイル名、またはトークンでアイテムを検索します。"},{"op":"ADDNEWCONTENTBUTTON.CAPTION","s":"新しいコンテンツ"},{"op":"CONTENTITEMLISTACTIONLABEL.CAPTION.LOAD","s":"アイテムを読み込んでいます..."},{"op":"CONTENTITEMLISTACTIONLABEL.CAPTION.LIMIT","s":"検索を絞り込んで、より多くのアイテムを表示します"},{"op":"CONTENTITEMLISTACTIONLABEL.CAPTION.EMPTY","s":"項目は見つかりませんでした"},{"op":"CONTENTITEMLISTACTIONLABEL.CAPTION.MORE","s":"もっと読み込む"},{"op":"CONTENTITEMSIZETEXT.CURRENTITEM.CAPTION.NEW","s":"新着"},{"op":"FOOTERTEXT.CAPTION","s":"ここでの設定は、ポータルで使用されるコンテンツアイテムに影響します。変更を慎重に検討してください"},{"op":"SHARING.ONGETLIBRARYITEMSFAILED","s":"ライブラリアイテムを読み込めないというエラー"},{"op":"ITEMFILEUPLOADOPTION.CAPTION","s":"ファイルのアップロード"},{"op":"ITEMYOUTTUBEMENUOPTION.CAPTION","s":"YouTubeビデオ"}]}